<?xml version="1.0" encoding="UTF-8" ?>
<!DOCTYPE mapper PUBLIC "-//mybatis.org//DTD Mapper 3.0//EN" "http://mybatis.org/dtd/mybatis-3-mapper.dtd" >
<mapper namespace="com.eco.mybatis.generate.mapper.FlWxCountMapper" >
  <resultMap id="BaseResultMap" type="com.eco.mybatis.generate.entity.FlWxCount" >
    <!--
      WARNING - @mbggenerated
      This element is automatically generated by MyBatis Generator, do not modify.
      This element was generated on Tue Jun 16 17:18:25 CST 2020.
    -->
    <id column="wechat_id" property="wechatId" jdbcType="INTEGER" />
    <result column="usermark_id" property="usermarkId" jdbcType="INTEGER" />
    <result column="ratio" property="ratio" jdbcType="INTEGER" />
    <result column="wechat_order_pay_number" property="wechatOrderPayNumber" jdbcType="INTEGER" />
    <result column="wechat_order_cancel_number" property="wechatOrderCancelNumber" jdbcType="INTEGER" />
    <result column="wechat_order_settle_number" property="wechatOrderSettleNumber" jdbcType="INTEGER" />
    <result column="wechat_order_delay_number" property="wechatOrderDelayNumber" jdbcType="INTEGER" />
    <result column="wechat_order_refund_number" property="wechatOrderRefundNumber" jdbcType="INTEGER" />
    <result column="wechat_order_search" property="wechatOrderSearch" jdbcType="INTEGER" />
    <result column="wechat_cash_number" property="wechatCashNumber" jdbcType="INTEGER" />
    <result column="wechat_share_number" property="wechatShareNumber" jdbcType="INTEGER" />
    <result column="wechat_share_buy_number" property="wechatShareBuyNumber" jdbcType="INTEGER" />
    <result column="wechat_search_wxid" property="wechatSearchWxid" jdbcType="VARCHAR" />
    <result column="wechat_cash_money" property="wechatCashMoney" jdbcType="DOUBLE" />
    <result column="wechat_search_time" property="wechatSearchTime" jdbcType="TIMESTAMP" />
    <result column="sign_number" property="signNumber" jdbcType="INTEGER" />
    <result column="taobao_number" property="taobaoNumber" jdbcType="INTEGER" />
    <result column="create_time" property="createTime" jdbcType="TIMESTAMP" />
    <result column="update_time" property="updateTime" jdbcType="TIMESTAMP" />
  </resultMap>
  <sql id="Base_Column_List" >
    <!--
      WARNING - @mbggenerated
      This element is automatically generated by MyBatis Generator, do not modify.
      This element was generated on Tue Jun 16 17:18:25 CST 2020.
    -->
    wechat_id, usermark_id, ratio, wechat_order_pay_number, wechat_order_cancel_number,
    wechat_order_settle_number, wechat_order_delay_number, wechat_order_refund_number,
    wechat_order_search, wechat_cash_number, wechat_share_number, wechat_share_buy_number,
    wechat_search_wxid, wechat_cash_money, wechat_search_time, sign_number, taobao_number,
    create_time, update_time
  </sql>
  <select id="selectByPrimaryKey" resultMap="BaseResultMap" parameterType="java.lang.Integer" >
    <!--
      WARNING - @mbggenerated
      This element is automatically generated by MyBatis Generator, do not modify.
      This element was generated on Tue Jun 16 17:18:25 CST 2020.
    -->
    select
    <include refid="Base_Column_List" />
    from fl_wx_count
    where wechat_id = #{wechatId,jdbcType=INTEGER}
  </select>
  <delete id="deleteByPrimaryKey" parameterType="java.lang.Integer" >
    <!--
      WARNING - @mbggenerated
      This element is automatically generated by MyBatis Generator, do not modify.
      This element was generated on Tue Jun 16 17:18:25 CST 2020.
    -->
    delete from fl_wx_count
    where wechat_id = #{wechatId,jdbcType=INTEGER}
  </delete>
  <insert id="insert" parameterType="com.eco.mybatis.generate.entity.FlWxCount" >
    <!--
      WARNING - @mbggenerated
      This element is automatically generated by MyBatis Generator, do not modify.
      This element was generated on Tue Jun 16 17:18:25 CST 2020.
    -->
    insert into fl_wx_count (wechat_id, usermark_id, ratio,
      wechat_order_pay_number, wechat_order_cancel_number,
      wechat_order_settle_number, wechat_order_delay_number,
      wechat_order_refund_number, wechat_order_search,
      wechat_cash_number, wechat_share_number, wechat_share_buy_number,
      wechat_search_wxid, wechat_cash_money, wechat_search_time,
      sign_number, taobao_number, create_time,
      update_time)
    values (#{wechatId,jdbcType=INTEGER}, #{usermarkId,jdbcType=INTEGER}, #{ratio,jdbcType=INTEGER},
      #{wechatOrderPayNumber,jdbcType=INTEGER}, #{wechatOrderCancelNumber,jdbcType=INTEGER},
      #{wechatOrderSettleNumber,jdbcType=INTEGER}, #{wechatOrderDelayNumber,jdbcType=INTEGER},
      #{wechatOrderRefundNumber,jdbcType=INTEGER}, #{wechatOrderSearch,jdbcType=INTEGER},
      #{wechatCashNumber,jdbcType=INTEGER}, #{wechatShareNumber,jdbcType=INTEGER}, #{wechatShareBuyNumber,jdbcType=INTEGER},
      #{wechatSearchWxid,jdbcType=VARCHAR}, #{wechatCashMoney,jdbcType=DOUBLE}, #{wechatSearchTime,jdbcType=TIMESTAMP},
      #{signNumber,jdbcType=INTEGER}, #{taobaoNumber,jdbcType=INTEGER}, #{createTime,jdbcType=TIMESTAMP},
      #{updateTime,jdbcType=TIMESTAMP})
  </insert>
  <insert id="insertSelective" parameterType="com.eco.mybatis.generate.entity.FlWxCount" >
    <!--
      WARNING - @mbggenerated
      This element is automatically generated by MyBatis Generator, do not modify.
      This element was generated on Tue Jun 16 17:18:25 CST 2020.
    -->
    insert into fl_wx_count
    <trim prefix="(" suffix=")" suffixOverrides="," >
      <if test="wechatId != null" >
        wechat_id,
      </if>
      <if test="usermarkId != null" >
        usermark_id,
      </if>
      <if test="ratio != null" >
        ratio,
      </if>
      <if test="wechatOrderPayNumber != null" >
        wechat_order_pay_number,
      </if>
      <if test="wechatOrderCancelNumber != null" >
        wechat_order_cancel_number,
      </if>
      <if test="wechatOrderSettleNumber != null" >
        wechat_order_settle_number,
      </if>
      <if test="wechatOrderDelayNumber != null" >
        wechat_order_delay_number,
      </if>
      <if test="wechatOrderRefundNumber != null" >
        wechat_order_refund_number,
      </if>
      <if test="wechatOrderSearch != null" >
        wechat_order_search,
      </if>
      <if test="wechatCashNumber != null" >
        wechat_cash_number,
      </if>
      <if test="wechatShareNumber != null" >
        wechat_share_number,
      </if>
      <if test="wechatShareBuyNumber != null" >
        wechat_share_buy_number,
      </if>
      <if test="wechatSearchWxid != null" >
        wechat_search_wxid,
      </if>
      <if test="wechatCashMoney != null" >
        wechat_cash_money,
      </if>
      <if test="wechatSearchTime != null" >
        wechat_search_time,
      </if>
      <if test="signNumber != null" >
        sign_number,
      </if>
      <if test="taobaoNumber != null" >
        taobao_number,
      </if>
      <if test="createTime != null" >
        create_time,
      </if>
      <if test="updateTime != null" >
        update_time,
      </if>
    </trim>
    <trim prefix="values (" suffix=")" suffixOverrides="," >
      <if test="wechatId != null" >
        #{wechatId,jdbcType=INTEGER},
      </if>
      <if test="usermarkId != null" >
        #{usermarkId,jdbcType=INTEGER},
      </if>
      <if test="ratio != null" >
        #{ratio,jdbcType=INTEGER},
      </if>
      <if test="wechatOrderPayNumber != null" >
        #{wechatOrderPayNumber,jdbcType=INTEGER},
      </if>
      <if test="wechatOrderCancelNumber != null" >
        #{wechatOrderCancelNumber,jdbcType=INTEGER},
      </if>
      <if test="wechatOrderSettleNumber != null" >
        #{wechatOrderSettleNumber,jdbcType=INTEGER},
      </if>
      <if test="wechatOrderDelayNumber != null" >
        #{wechatOrderDelayNumber,jdbcType=INTEGER},
      </if>
      <if test="wechatOrderRefundNumber != null" >
        #{wechatOrderRefundNumber,jdbcType=INTEGER},
      </if>
      <if test="wechatOrderSearch != null" >
        #{wechatOrderSearch,jdbcType=INTEGER},
      </if>
      <if test="wechatCashNumber != null" >
        #{wechatCashNumber,jdbcType=INTEGER},
      </if>
      <if test="wechatShareNumber != null" >
        #{wechatShareNumber,jdbcType=INTEGER},
      </if>
      <if test="wechatShareBuyNumber != null" >
        #{wechatShareBuyNumber,jdbcType=INTEGER},
      </if>
      <if test="wechatSearchWxid != null" >
        #{wechatSearchWxid,jdbcType=VARCHAR},
      </if>
      <if test="wechatCashMoney != null" >
        #{wechatCashMoney,jdbcType=DOUBLE},
      </if>
      <if test="wechatSearchTime != null" >
        #{wechatSearchTime,jdbcType=TIMESTAMP},
      </if>
      <if test="signNumber != null" >
        #{signNumber,jdbcType=INTEGER},
      </if>
      <if test="taobaoNumber != null" >
        #{taobaoNumber,jdbcType=INTEGER},
      </if>
      <if test="createTime != null" >
        #{createTime,jdbcType=TIMESTAMP},
      </if>
      <if test="updateTime != null" >
        #{updateTime,jdbcType=TIMESTAMP},
      </if>
    </trim>
  </insert>
  <update id="updateByPrimaryKeySelective" parameterType="com.eco.mybatis.generate.entity.FlWxCount" >
    <!--
      WARNING - @mbggenerated
      This element is automatically generated by MyBatis Generator, do not modify.
      This element was generated on Tue Jun 16 17:18:25 CST 2020.
    -->
    update fl_wx_count
    <set >
      <if test="usermarkId != null" >
        usermark_id = #{usermarkId,jdbcType=INTEGER},
      </if>
      <if test="ratio != null" >
        ratio = #{ratio,jdbcType=INTEGER},
      </if>
      <if test="wechatOrderPayNumber != null" >
        wechat_order_pay_number = #{wechatOrderPayNumber,jdbcType=INTEGER},
      </if>
      <if test="wechatOrderCancelNumber != null" >
        wechat_order_cancel_number = #{wechatOrderCancelNumber,jdbcType=INTEGER},
      </if>
      <if test="wechatOrderSettleNumber != null" >
        wechat_order_settle_number = #{wechatOrderSettleNumber,jdbcType=INTEGER},
      </if>
      <if test="wechatOrderDelayNumber != null" >
        wechat_order_delay_number = #{wechatOrderDelayNumber,jdbcType=INTEGER},
      </if>
      <if test="wechatOrderRefundNumber != null" >
        wechat_order_refund_number = #{wechatOrderRefundNumber,jdbcType=INTEGER},
      </if>
      <if test="wechatOrderSearch != null" >
        wechat_order_search = #{wechatOrderSearch,jdbcType=INTEGER},
      </if>
      <if test="wechatCashNumber != null" >
        wechat_cash_number = #{wechatCashNumber,jdbcType=INTEGER},
      </if>
      <if test="wechatShareNumber != null" >
        wechat_share_number = #{wechatShareNumber,jdbcType=INTEGER},
      </if>
      <if test="wechatShareBuyNumber != null" >
        wechat_share_buy_number = #{wechatShareBuyNumber,jdbcType=INTEGER},
      </if>
      <if test="wechatSearchWxid != null" >
        wechat_search_wxid = #{wechatSearchWxid,jdbcType=VARCHAR},
      </if>
      <if test="wechatCashMoney != null" >
        wechat_cash_money = #{wechatCashMoney,jdbcType=DOUBLE},
      </if>
      <if test="wechatSearchTime != null" >
        wechat_search_time = #{wechatSearchTime,jdbcType=TIMESTAMP},
      </if>
      <if test="signNumber != null" >
        sign_number = #{signNumber,jdbcType=INTEGER},
      </if>
      <if test="taobaoNumber != null" >
        taobao_number = #{taobaoNumber,jdbcType=INTEGER},
      </if>
      <if test="createTime != null" >
        create_time = #{createTime,jdbcType=TIMESTAMP},
      </if>
      <if test="updateTime != null" >
        update_time = #{updateTime,jdbcType=TIMESTAMP},
      </if>
    </set>
    where wechat_id = #{wechatId,jdbcType=INTEGER}
  </update>
  <update id="updateByPrimaryKey" parameterType="com.eco.mybatis.generate.entity.FlWxCount" >
    <!--
      WARNING - @mbggenerated
      This element is automatically generated by MyBatis Generator, do not modify.
      This element was generated on Tue Jun 16 17:18:25 CST 2020.
    -->
    update fl_wx_count
    set usermark_id = #{usermarkId,jdbcType=INTEGER},
      ratio = #{ratio,jdbcType=INTEGER},
      wechat_order_pay_number = #{wechatOrderPayNumber,jdbcType=INTEGER},
      wechat_order_cancel_number = #{wechatOrderCancelNumber,jdbcType=INTEGER},
      wechat_order_settle_number = #{wechatOrderSettleNumber,jdbcType=INTEGER},
      wechat_order_delay_number = #{wechatOrderDelayNumber,jdbcType=INTEGER},
      wechat_order_refund_number = #{wechatOrderRefundNumber,jdbcType=INTEGER},
      wechat_order_search = #{wechatOrderSearch,jdbcType=INTEGER},
      wechat_cash_number = #{wechatCashNumber,jdbcType=INTEGER},
      wechat_share_number = #{wechatShareNumber,jdbcType=INTEGER},
      wechat_share_buy_number = #{wechatShareBuyNumber,jdbcType=INTEGER},
      wechat_search_wxid = #{wechatSearchWxid,jdbcType=VARCHAR},
      wechat_cash_money = #{wechatCashMoney,jdbcType=DOUBLE},
      wechat_search_time = #{wechatSearchTime,jdbcType=TIMESTAMP},
      sign_number = #{signNumber,jdbcType=INTEGER},
      taobao_number = #{taobaoNumber,jdbcType=INTEGER},
      create_time = #{createTime,jdbcType=TIMESTAMP},
      update_time = #{updateTime,jdbcType=TIMESTAMP}
    where wechat_id = #{wechatId,jdbcType=INTEGER}
  </update>
</mapper>